odoo/addons/l10n_nl_bank/README.rst
odoo/addons/l10n_nl_bank/__init__.py
odoo/addons/l10n_nl_bank/__manifest__.py
odoo/addons/l10n_nl_bank/data/res_bank_data.xml
odoo/addons/l10n_nl_bank/i18n/l10n_nl_bank.pot
odoo/addons/l10n_nl_bank/readme/CONTRIBUTORS.rst
odoo/addons/l10n_nl_bank/readme/CREDITS.rst
odoo/addons/l10n_nl_bank/readme/DESCRIPTION.rst
odoo/addons/l10n_nl_bank/static/description/icon.png
odoo/addons/l10n_nl_bank/static/description/icon.svg
odoo/addons/l10n_nl_bank/static/description/index.html
odoo12_addon_l10n_nl_bank-12.0.1.0.0.99.dev4.dist-info/METADATA
odoo12_addon_l10n_nl_bank-12.0.1.0.0.99.dev4.dist-info/WHEEL
odoo12_addon_l10n_nl_bank-12.0.1.0.0.99.dev4.dist-info/top_level.txt
odoo12_addon_l10n_nl_bank-12.0.1.0.0.99.dev4.dist-info/RECORD
